<?xml version="1.0" encoding="utf-8"?>
                        <nfeProc  versao="4.00" xmlns="http://www.portalfiscal.inf.br/nfe"><protNFe><infProt><nProt>141250015046096</nProt><digVal>QF1J2k+yxk+OM4KceTg6pU3s4vg=</digVal><dhRecbto>2025-01-15T14:17:06-03:00</dhRecbto><Id>ID141250015046096</Id><chNFe>41250104349342000687550010000136551597595009</chNFe><xMotivo>Autorizado o uso da NF-e</xMotivo><cStat>100</cStat></infProt></protNFe><NFe><infNFe Id="NFe41250104349342000687550010000136551597595009"><infAdic><infCpl>ICMS C/ DIFERIMENTO PARCIAL DE 38,46% CONFORME ART. 28 DO ANEXO 08, INCISO I DECRETO 7871/2017 RICMS-PR. Nro do Pedido: 14604</infCpl></infAdic><infRespTec><fone>3432390700</fone><CNPJ>26314062000161</CNPJ><xContato>Fabio Tulio Felippe</xContato><email>marketing@sankhya.com.br</email></infRespTec><det><nItem>1</nItem><prod><xPed>14604</xPed><cEAN>SEM GTIN</cEAN><cProd>242002</cProd><qCom>10.75</qCom><cEANTrib>SEM GTIN</cEANTrib><vUnTrib>49.7674418605</vUnTrib><cBenef>PR830001</cBenef><qTrib>10.75</qTrib><vProd>535.00</vProd><xProd>TELHA TERMOACUSTICA EPS 30MM AZ150 TR25 0,43MM 1F</xProd><vUnCom>49.7674418605</vUnCom><nItemPed>1</nItemPed><indTot>1</indTot><uTrib>MT</uTrib><NCM>73089090</NCM><uCom>MT</uCom><CFOP>5101</CFOP><CEST>1005000</CEST><EXTIPI>01</EXTIPI></prod><imposto><vTotTrib>136.16</vTotTrib><ICMS><ICMS51><modBC>3</modBC><vICMSDif>40.13</vICMSDif><vICMSOp>104.33</vICMSOp><pDif>38.4600</pDif><pRedBC>0.0000</pRedBC><orig>0</orig><CST>51</CST><vBC>535.00</vBC><vICMS>64.20</vICMS><pICMS>19.50</pICMS></ICMS51></ICMS><COFINS><COFINSAliq><vCOFINS>35.78</vCOFINS><CST>01</CST><vBC>470.80</vBC><pCOFINS>7.6000</pCOFINS></COFINSAliq></COFINS><PIS><PISAliq><vPIS>7.77</vPIS><CST>01</CST><vBC>470.80</vBC><pPIS>1.6500</pPIS></PISAliq></PIS></imposto><infAdProd>Lote: 1654/202501</infAdProd></det><total><ICMSTot><vCOFINS>35.78</vCOFINS><vBCST>0.00</vBCST><vICMSDeson>0.00</vICMSDeson><vProd>535.00</vProd><vSeg>0.00</vSeg><vFCP>0.00</vFCP><vFCPST>0.00</vFCPST><vNF>535.00</vNF><vTotTrib>136.16</vTotTrib><vPIS>7.77</vPIS><vIPIDevol>0.00</vIPIDevol><vBC>535.00</vBC><vST>0.00</vST><vICMS>64.20</vICMS><vII>0.00</vII><vFCPSTRet>0.00</vFCPSTRet><vDesc>0.00</vDesc><vOutro>0.00</vOutro><vIPI>0.00</vIPI><vFrete>0.00</vFrete></ICMSTot></total><cobr><fat><vOrig>535.00</vOrig><nFat>13655</nFat><vDesc>0.00</vDesc><vLiq>535.00</vLiq></fat><dup><dVenc>2025-02-14</dVenc><nDup>001</nDup><vDup>535.00</vDup></dup></cobr><pag><detPag><vPag>535.00</vPag><tPag>15</tPag><indPag>1</indPag></detPag></pag><ide><tpNF>1</tpNF><mod>55</mod><indPres>0</indPres><tpImp>1</tpImp><nNF>13655</nNF><cMunFG>4109401</cMunFG><procEmi>0</procEmi><finNFe>1</finNFe><dhEmi>2025-01-15T14:17:04-03:00</dhEmi><tpAmb>1</tpAmb><indFinal>1</indFinal><dhSaiEnt>2025-01-15T14:17:04-03:00</dhSaiEnt><idDest>1</idDest><tpEmis>1</tpEmis><cDV>9</cDV><cUF>41</cUF><serie>1</serie><natOp>Sai/DE/Cpa de prod do estabel</natOp><cNF>59759500</cNF><verProc>4.28b183</verProc></ide><Id>NFe41250104349342000687550010000136551597595009</Id><autXML><CPF>38722437991</CPF></autXML><dest><xNome>C F DOS SANTOS ESTRUTURAS</xNome><CNPJ>58020494000156</CNPJ><enderDest><xCpl>SALA 01</xCpl><fone>554298523789</fone><UF>PR</UF><xPais>Brasil</xPais><cPais>1058</cPais><xLgr>R PROFESSOR PARAILHO MACHADO</xLgr><xMun>CANDOI</xMun><nro>311</nro><cMun>4104428</cMun><xBairro>CENTRO</xBairro><CEP>85140000</CEP></enderDest><IE>9110767568</IE><indIEDest>1</indIEDest><email>tormec_@hotmail.com</email></dest><emit><xNome>TELHAS CASCAVEL LTDA</xNome><CRT>3</CRT><xFant>TELHACO GPV</xFant><CNPJ>04349342000687</CNPJ><enderEmit><fone>04233043177</fone><UF>PR</UF><xPais>Brasil</xPais><cPais>1058</cPais><xLgr>Ave BENTO MUNHOZ DA ROCHA NETO</xLgr><xMun>GUARAPUAVA</xMun><nro>2460</nro><cMun>4109401</cMun><xBairro>ALDEIA</xBairro><CEP>85050150</CEP></enderEmit><IE>9092049172</IE></emit><transp><modFrete>0</modFrete><vol><pesoL>44.193</pesoL><qVol>11</qVol><pesoB>44.193</pesoB></vol></transp></infNFe></NFe><versao>4.00</versao></nfeProc>